[
  {
    "Domain": "Vehicle.State",
    "KUKSA_Path": "Vehicle.State.IgnitionState",
    "Type": "string",
    "Unit": "",
    "Owner_Service": "Vehicle Core Services",
    "Source": "CAN Gateway",
    "Dashboard": "Y",
    "UVI_Companion": "Y",
    "Episode_Used": "Y",
    "Description": "KL15/ignition state"
  },
  {
    "Domain": "Vehicle.State",
    "KUKSA_Path": "Vehicle.State.PowerMode",
    "Type": "string",
    "Unit": "",
    "Owner_Service": "Vehicle Core Services",
    "Source": "CAN Gateway",
    "Dashboard": "Y",
    "UVI_Companion": "Y",
    "Episode_Used": "Y",
    "Description": "Off/accessory/ready/driving"
  },
  {
    "Domain": "Vehicle.State",
    "KUKSA_Path": "Vehicle.State.Speed",
    "Type": "float",
    "Unit": "km/h",
    "Owner_Service": "Vehicle Core Services",
    "Source": "CAN Gateway",
    "Dashboard": "Y",
    "UVI_Companion": "Y",
    "Episode_Used": "Y",
    "Description": "Current vehicle speed"
  },
  {
    "Domain": "Vehicle.State",
    "KUKSA_Path": "Vehicle.State.Acceleration",
    "Type": "float",
    "Unit": "m/s2",
    "Owner_Service": "Vehicle Core Services",
    "Source": "CAN Gateway",
    "Dashboard": "Y",
    "UVI_Companion": "Y",
    "Episode_Used": "Y",
    "Description": "Vehicle acceleration"
  },
  {
    "Domain": "Vehicle.State",
    "KUKSA_Path": "Vehicle.State.GearPosition",
    "Type": "string",
    "Unit": "",
    "Owner_Service": "Vehicle Core Services",
    "Source": "CAN Gateway",
    "Dashboard": "Y",
    "UVI_Companion": "Y",
    "Episode_Used": "Y",
    "Description": "P/R/N/D gear state"
  },
  {
    "Domain": "Vehicle.State",
    "KUKSA_Path": "Vehicle.State.DriveMode",
    "Type": "string",
    "Unit": "",
    "Owner_Service": "Vehicle Core Services",
    "Source": "CAN Gateway",
    "Dashboard": "Y",
    "UVI_Companion": "Y",
    "Episode_Used": "Y",
    "Description": "Eco/comfort/sport/snow"
  },
  {
    "Domain": "Vehicle.State",
    "KUKSA_Path": "Vehicle.State.VehicleMoving",
    "Type": "boolean",
    "Unit": "",
    "Owner_Service": "Vehicle Core Services",
    "Source": "CAN Gateway",
    "Dashboard": "Y",
    "UVI_Companion": "Y",
    "Episode_Used": "Y",
    "Description": "Whether vehicle is moving"
  },
  {
    "Domain": "Vehicle.State",
    "KUKSA_Path": "Vehicle.State.VehicleLocked",
    "Type": "boolean",
    "Unit": "",
    "Owner_Service": "Body Services",
    "Source": "CAN Gateway",
    "Dashboard": "Y",
    "UVI_Companion": "Y",
    "Episode_Used": "Y",
    "Description": "Lock state"
  },
  {
    "Domain": "Vehicle.State",
    "KUKSA_Path": "Vehicle.State.Odometer",
    "Type": "float",
    "Unit": "km",
    "Owner_Service": "Vehicle Core Services",
    "Source": "CAN Gateway",
    "Dashboard": "Y",
    "UVI_Companion": "N",
    "Episode_Used": "N",
    "Description": "Lifetime distance"
  },
  {
    "Domain": "Vehicle.State",
    "KUKSA_Path": "Vehicle.State.TripDistance",
    "Type": "float",
    "Unit": "km",
    "Owner_Service": "Vehicle Core Services",
    "Source": "CAN Gateway",
    "Dashboard": "Y",
    "UVI_Companion": "Y",
    "Episode_Used": "Y",
    "Description": "Current trip distance"
  },
  {
    "Domain": "Vehicle.State",
    "KUKSA_Path": "Vehicle.State.TripDuration",
    "Type": "integer",
    "Unit": "min",
    "Owner_Service": "Vehicle Core Services",
    "Source": "CAN Gateway",
    "Dashboard": "Y",
    "UVI_Companion": "Y",
    "Episode_Used": "Y",
    "Description": "Current trip duration"
  },
  {
    "Domain": "Vehicle.State",
    "KUKSA_Path": "Vehicle.State.ParkedDuration",
    "Type": "integer",
    "Unit": "min",
    "Owner_Service": "Vehicle Core Services",
    "Source": "CAN Gateway",
    "Dashboard": "Y",
    "UVI_Companion": "Y",
    "Episode_Used": "Y",
    "Description": "Parked duration"
  },
  {
    "Domain": "Vehicle.State",
    "KUKSA_Path": "Vehicle.State.CurrentLatitude",
    "Type": "float",
    "Unit": "deg",
    "Owner_Service": "Connectivity Services",
    "Source": "GPS/Cloud",
    "Dashboard": "N",
    "UVI_Companion": "Y",
    "Episode_Used": "Y",
    "Description": "Current latitude"
  },
  {
    "Domain": "Vehicle.State",
    "KUKSA_Path": "Vehicle.State.CurrentLongitude",
    "Type": "float",
    "Unit": "deg",
    "Owner_Service": "Connectivity Services",
    "Source": "GPS/Cloud",
    "Dashboard": "N",
    "UVI_Companion": "Y",
    "Episode_Used": "Y",
    "Description": "Current longitude"
  },
  {
    "Domain": "Vehicle.State",
    "KUKSA_Path": "Vehicle.State.Heading",
    "Type": "float",
    "Unit": "deg",
    "Owner_Service": "Connectivity Services",
    "Source": "GPS/IMU",
    "Dashboard": "Y",
    "UVI_Companion": "N",
    "Episode_Used": "Y",
    "Description": "Vehicle heading"
  },
  {
    "Domain": "Powertrain.Energy",
    "KUKSA_Path": "Vehicle.Powertrain.MotorRPM",
    "Type": "integer",
    "Unit": "rpm",
    "Owner_Service": "Powertrain Services",
    "Source": "CAN Gateway",
    "Dashboard": "N",
    "UVI_Companion": "N",
    "Episode_Used": "Y",
    "Description": "Motor speed"
  },
  {
    "Domain": "Powertrain.Energy",
    "KUKSA_Path": "Vehicle.Powertrain.MotorTorque",
    "Type": "float",
    "Unit": "Nm",
    "Owner_Service": "Powertrain Services",
    "Source": "CAN Gateway",
    "Dashboard": "N",
    "UVI_Companion": "N",
    "Episode_Used": "Y",
    "Description": "Motor torque"
  },
  {
    "Domain": "Powertrain.Energy",
    "KUKSA_Path": "Vehicle.Powertrain.MotorPower",
    "Type": "float",
    "Unit": "kW",
    "Owner_Service": "Powertrain Services",
    "Source": "CAN Gateway",
    "Dashboard": "Y",
    "UVI_Companion": "Y",
    "Episode_Used": "Y",
    "Description": "Motor output power"
  },
  {
    "Domain": "Powertrain.Energy",
    "KUKSA_Path": "Vehicle.Powertrain.PowerLimitActive",
    "Type": "boolean",
    "Unit": "",
    "Owner_Service": "Powertrain Services",
    "Source": "CAN Gateway",
    "Dashboard": "Y",
    "UVI_Companion": "Y",
    "Episode_Used": "Y",
    "Description": "Power limiting state"
  },
  {
    "Domain": "Powertrain.Energy",
    "KUKSA_Path": "Vehicle.Powertrain.EnergyEfficiencyScore",
    "Type": "float",
    "Unit": "score",
    "Owner_Service": "Powertrain Services",
    "Source": "CAN Gateway",
    "Dashboard": "Y",
    "UVI_Companion": "Y",
    "Episode_Used": "Y",
    "Description": "Efficiency score"
  },
  {
    "Domain": "Powertrain.Energy",
    "KUKSA_Path": "Vehicle.EVBattery.StateOfCharge",
    "Type": "float",
    "Unit": "%",
    "Owner_Service": "Powertrain Services",
    "Source": "CAN Gateway",
    "Dashboard": "Y",
    "UVI_Companion": "Y",
    "Episode_Used": "Y",
    "Description": "Battery SOC"
  },
  {
    "Domain": "Powertrain.Energy",
    "KUKSA_Path": "Vehicle.EVBattery.StateOfHealth",
    "Type": "float",
    "Unit": "%",
    "Owner_Service": "Powertrain Services",
    "Source": "CAN Gateway",
    "Dashboard": "Y",
    "UVI_Companion": "Y",
    "Episode_Used": "Y",
    "Description": "Battery SOH"
  },
  {
    "Domain": "Powertrain.Energy",
    "KUKSA_Path": "Vehicle.EVBattery.EstimatedRange",
    "Type": "float",
    "Unit": "km",
    "Owner_Service": "Powertrain Services",
    "Source": "CAN Gateway",
    "Dashboard": "Y",
    "UVI_Companion": "Y",
    "Episode_Used": "Y",
    "Description": "Estimated EV range"
  },
  {
    "Domain": "Powertrain.Energy",
    "KUKSA_Path": "Vehicle.EVBattery.ArrivalSOC",
    "Type": "float",
    "Unit": "%",
    "Owner_Service": "Powertrain Services",
    "Source": "Navigation",
    "Dashboard": "Y",
    "UVI_Companion": "Y",
    "Episode_Used": "Y",
    "Description": "Predicted arrival SOC"
  },
  {
    "Domain": "Powertrain.Energy",
    "KUKSA_Path": "Vehicle.EVBattery.Temperature",
    "Type": "float",
    "Unit": "C",
    "Owner_Service": "Powertrain Services",
    "Source": "CAN Gateway",
    "Dashboard": "Y",
    "UVI_Companion": "Y",
    "Episode_Used": "Y",
    "Description": "Battery pack temperature"
  },
  {
    "Domain": "Powertrain.Energy",
    "KUKSA_Path": "Vehicle.EVBattery.Voltage",
    "Type": "float",
    "Unit": "V",
    "Owner_Service": "Powertrain Services",
    "Source": "CAN Gateway",
    "Dashboard": "N",
    "UVI_Companion": "Y",
    "Episode_Used": "N",
    "Description": "Battery voltage"
  },
  {
    "Domain": "Powertrain.Energy",
    "KUKSA_Path": "Vehicle.EVBattery.Current",
    "Type": "float",
    "Unit": "A",
    "Owner_Service": "Powertrain Services",
    "Source": "CAN Gateway",
    "Dashboard": "N",
    "UVI_Companion": "Y",
    "Episode_Used": "N",
    "Description": "Battery current"
  },
  {
    "Domain": "Powertrain.Energy",
    "KUKSA_Path": "Vehicle.EVBattery.PowerDraw",
    "Type": "float",
    "Unit": "kW",
    "Owner_Service": "Powertrain Services",
    "Source": "CAN Gateway",
    "Dashboard": "Y",
    "UVI_Companion": "Y",
    "Episode_Used": "Y",
    "Description": "Current power draw"
  },
  {
    "Domain": "Powertrain.Energy",
    "KUKSA_Path": "Vehicle.EVBattery.LowBatteryWarning",
    "Type": "boolean",
    "Unit": "",
    "Owner_Service": "Powertrain Services",
    "Source": "CAN Gateway",
    "Dashboard": "Y",
    "UVI_Companion": "Y",
    "Episode_Used": "Y",
    "Description": "Low battery warning"
  },
  {
    "Domain": "Powertrain.Energy",
    "KUKSA_Path": "Vehicle.EVBattery.ThermalWarning",
    "Type": "boolean",
    "Unit": "",
    "Owner_Service": "Powertrain Services",
    "Source": "CAN Gateway",
    "Dashboard": "Y",
    "UVI_Companion": "Y",
    "Episode_Used": "Y",
    "Description": "Battery thermal warning"
  },
  {
    "Domain": "Powertrain.Energy",
    "KUKSA_Path": "Vehicle.EVBattery.DegradationRisk",
    "Type": "string",
    "Unit": "",
    "Owner_Service": "Powertrain Services",
    "Source": "Model",
    "Dashboard": "N",
    "UVI_Companion": "Y",
    "Episode_Used": "Y",
    "Description": "Battery aging risk"
  },
  {
    "Domain": "Powertrain.Energy",
    "KUKSA_Path": "Vehicle.Charging.PortOpen",
    "Type": "boolean",
    "Unit": "",
    "Owner_Service": "Powertrain Services",
    "Source": "CAN Gateway",
    "Dashboard": "Y",
    "UVI_Companion": "N",
    "Episode_Used": "N",
    "Description": "Charging port state"
  },
  {
    "Domain": "Powertrain.Energy",
    "KUKSA_Path": "Vehicle.Charging.CableConnected",
    "Type": "boolean",
    "Unit": "",
    "Owner_Service": "Powertrain Services",
    "Source": "CAN Gateway",
    "Dashboard": "Y",
    "UVI_Companion": "Y",
    "Episode_Used": "Y",
    "Description": "Cable connected"
  },
  {
    "Domain": "Powertrain.Energy",
    "KUKSA_Path": "Vehicle.Charging.ChargingActive",
    "Type": "boolean",
    "Unit": "",
    "Owner_Service": "Powertrain Services",
    "Source": "CAN Gateway",
    "Dashboard": "Y",
    "UVI_Companion": "Y",
    "Episode_Used": "Y",
    "Description": "Charging active"
  },
  {
    "Domain": "Powertrain.Energy",
    "KUKSA_Path": "Vehicle.Charging.ChargingPower",
    "Type": "float",
    "Unit": "kW",
    "Owner_Service": "Powertrain Services",
    "Source": "CAN Gateway",
    "Dashboard": "Y",
    "UVI_Companion": "Y",
    "Episode_Used": "N",
    "Description": "Charging power"
  },
  {
    "Domain": "Powertrain.Energy",
    "KUKSA_Path": "Vehicle.Charging.TimeToFull",
    "Type": "integer",
    "Unit": "min",
    "Owner_Service": "Powertrain Services",
    "Source": "CAN Gateway",
    "Dashboard": "Y",
    "UVI_Companion": "Y",
    "Episode_Used": "N",
    "Description": "Estimated full charge time"
  },
  {
    "Domain": "Powertrain.Energy",
    "KUKSA_Path": "Vehicle.Charging.NearestChargerAvailable",
    "Type": "boolean",
    "Unit": "",
    "Owner_Service": "Connectivity Services",
    "Source": "Cloud/POI",
    "Dashboard": "Y",
    "UVI_Companion": "Y",
    "Episode_Used": "Y",
    "Description": "Nearby charger available"
  },
  {
    "Domain": "Powertrain.Energy",
    "KUKSA_Path": "Vehicle.Charging.NearestChargerDistance",
    "Type": "float",
    "Unit": "km",
    "Owner_Service": "Connectivity Services",
    "Source": "Cloud/POI",
    "Dashboard": "Y",
    "UVI_Companion": "Y",
    "Episode_Used": "Y",
    "Description": "Distance to charger"
  },
  {
    "Domain": "Powertrain.Energy",
    "KUKSA_Path": "Vehicle.Charging.QueueStatus",
    "Type": "string",
    "Unit": "",
    "Owner_Service": "Connectivity Services",
    "Source": "Cloud/POI",
    "Dashboard": "Y",
    "UVI_Companion": "Y",
    "Episode_Used": "Y",
    "Description": "Charger queue state"
  },
  {
    "Domain": "Powertrain.Energy",
    "KUKSA_Path": "Vehicle.Charging.PriceLevel",
    "Type": "string",
    "Unit": "",
    "Owner_Service": "Connectivity Services",
    "Source": "Cloud/POI",
    "Dashboard": "Y",
    "UVI_Companion": "Y",
    "Episode_Used": "Y",
    "Description": "Charging price level"
  },
  {
    "Domain": "Powertrain.Energy",
    "KUKSA_Path": "Vehicle.Charging.FastChargingAvailable",
    "Type": "boolean",
    "Unit": "",
    "Owner_Service": "Connectivity Services",
    "Source": "Cloud/POI",
    "Dashboard": "Y",
    "UVI_Companion": "Y",
    "Episode_Used": "Y",
    "Description": "Fast charger available"
  },
  {
    "Domain": "Powertrain.Energy",
    "KUKSA_Path": "Vehicle.Fuel.Level",
    "Type": "float",
    "Unit": "%",
    "Owner_Service": "Powertrain Services",
    "Source": "CAN Gateway",
    "Dashboard": "Y",
    "UVI_Companion": "Y",
    "Episode_Used": "N",
    "Description": "Fuel level for ICE/hybrid"
  },
  {
    "Domain": "Powertrain.Energy",
    "KUKSA_Path": "Vehicle.Fuel.Range",
    "Type": "float",
    "Unit": "km",
    "Owner_Service": "Powertrain Services",
    "Source": "CAN Gateway",
    "Dashboard": "Y",
    "UVI_Companion": "Y",
    "Episode_Used": "N",
    "Description": "Fuel range"
  },
  {
    "Domain": "Powertrain.Energy",
    "KUKSA_Path": "Vehicle.Fuel.LowFuelWarning",
    "Type": "boolean",
    "Unit": "",
    "Owner_Service": "Powertrain Services",
    "Source": "CAN Gateway",
    "Dashboard": "Y",
    "UVI_Companion": "Y",
    "Episode_Used": "N",
    "Description": "Low fuel warning"
  },
  {
    "Domain": "Powertrain.Energy",
    "KUKSA_Path": "Vehicle.Thermal.BatteryTemperature",
    "Type": "float",
    "Unit": "C",
    "Owner_Service": "Powertrain Services",
    "Source": "CAN Gateway",
    "Dashboard": "Y",
    "UVI_Companion": "Y",
    "Episode_Used": "Y",
    "Description": "Battery thermal signal"
  },
  {
    "Domain": "Powertrain.Energy",
    "KUKSA_Path": "Vehicle.Thermal.MotorTemperature",
    "Type": "float",
    "Unit": "C",
    "Owner_Service": "Powertrain Services",
    "Source": "CAN Gateway",
    "Dashboard": "Y",
    "UVI_Companion": "Y",
    "Episode_Used": "Y",
    "Description": "Motor temperature"
  },
  {
    "Domain": "Powertrain.Energy",
    "KUKSA_Path": "Vehicle.Thermal.BrakeTemperature",
    "Type": "float",
    "Unit": "C",
    "Owner_Service": "Chassis Services",
    "Source": "CAN Gateway",
    "Dashboard": "Y",
    "UVI_Companion": "Y",
    "Episode_Used": "Y",
    "Description": "Brake temperature"
  },
  {
    "Domain": "Powertrain.Energy",
    "KUKSA_Path": "Vehicle.Thermal.CoolingActive",
    "Type": "boolean",
    "Unit": "",
    "Owner_Service": "Powertrain Services",
    "Source": "CAN Gateway",
    "Dashboard": "Y",
    "UVI_Companion": "Y",
    "Episode_Used": "Y",
    "Description": "Thermal cooling active"
  },
  {
    "Domain": "Chassis.ADAS",
    "KUKSA_Path": "Vehicle.Chassis.RoadRoughness",
    "Type": "string",
    "Unit": "",
    "Owner_Service": "Chassis Services",
    "Source": "CAN Gateway",
    "Dashboard": "Y",
    "UVI_Companion": "Y",
    "Episode_Used": "Y",
    "Description": "Road roughness"
  },
  {
    "Domain": "Chassis.ADAS",
    "KUKSA_Path": "Vehicle.Chassis.RoadFriction",
    "Type": "float",
    "Unit": "coeff",
    "Owner_Service": "Chassis Services",
    "Source": "CAN Gateway",
    "Dashboard": "Y",
    "UVI_Companion": "Y",
    "Episode_Used": "Y",
    "Description": "Estimated friction"
  },
  {
    "Domain": "Chassis.ADAS",
    "KUKSA_Path": "Vehicle.Chassis.PotholeDetected",
    "Type": "boolean",
    "Unit": "",
    "Owner_Service": "Chassis Services",
    "Source": "CAN Gateway",
    "Dashboard": "Y",
    "UVI_Companion": "Y",
    "Episode_Used": "Y",
    "Description": "Pothole detected"
  },
  {
    "Domain": "Chassis.ADAS",
    "KUKSA_Path": "Vehicle.Chassis.StabilityControlActive",
    "Type": "boolean",
    "Unit": "",
    "Owner_Service": "Chassis Services",
    "Source": "CAN Gateway",
    "Dashboard": "Y",
    "UVI_Companion": "Y",
    "Episode_Used": "Y",
    "Description": "ESC active"
  },
  {
    "Domain": "Chassis.ADAS",
    "KUKSA_Path": "Vehicle.Chassis.TractionControlActive",
    "Type": "boolean",
    "Unit": "",
    "Owner_Service": "Chassis Services",
    "Source": "CAN Gateway",
    "Dashboard": "Y",
    "UVI_Companion": "Y",
    "Episode_Used": "Y",
    "Description": "TCS active"
  },
  {
    "Domain": "Chassis.ADAS",
    "KUKSA_Path": "Vehicle.Braking.BrakeHealth",
    "Type": "string",
    "Unit": "",
    "Owner_Service": "Chassis Services",
    "Source": "CAN Gateway",
    "Dashboard": "Y",
    "UVI_Companion": "Y",
    "Episode_Used": "Y",
    "Description": "Brake health"
  },
  {
    "Domain": "Chassis.ADAS",
    "KUKSA_Path": "Vehicle.Braking.PadWearPercent",
    "Type": "float",
    "Unit": "%",
    "Owner_Service": "Chassis Services",
    "Source": "CAN Gateway",
    "Dashboard": "Y",
    "UVI_Companion": "Y",
    "Episode_Used": "Y",
    "Description": "Brake pad wear"
  },
  {
    "Domain": "Chassis.ADAS",
    "KUKSA_Path": "Vehicle.Braking.HarshBrakingCount",
    "Type": "integer",
    "Unit": "count",
    "Owner_Service": "Chassis Services",
    "Source": "CAN Gateway",
    "Dashboard": "Y",
    "UVI_Companion": "Y",
    "Episode_Used": "Y",
    "Description": "Harsh braking count"
  },
  {
    "Domain": "Chassis.ADAS",
    "KUKSA_Path": "Vehicle.Braking.ABSActive",
    "Type": "boolean",
    "Unit": "",
    "Owner_Service": "Chassis Services",
    "Source": "CAN Gateway",
    "Dashboard": "Y",
    "UVI_Companion": "Y",
    "Episode_Used": "Y",
    "Description": "ABS active"
  },
  {
    "Domain": "Chassis.ADAS",
    "KUKSA_Path": "Vehicle.Steering.Angle",
    "Type": "float",
    "Unit": "deg",
    "Owner_Service": "Chassis Services",
    "Source": "CAN Gateway",
    "Dashboard": "Y",
    "UVI_Companion": "N",
    "Episode_Used": "Y",
    "Description": "Steering angle"
  },
  {
    "Domain": "Chassis.ADAS",
    "KUKSA_Path": "Vehicle.Steering.LateCorrectionsDetected",
    "Type": "boolean",
    "Unit": "",
    "Owner_Service": "Chassis Services",
    "Source": "CAN Gateway",
    "Dashboard": "N",
    "UVI_Companion": "Y",
    "Episode_Used": "Y",
    "Description": "Late corrections"
  },
  {
    "Domain": "Chassis.ADAS",
    "KUKSA_Path": "Vehicle.Steering.FrequentCorrectionsDetected",
    "Type": "boolean",
    "Unit": "",
    "Owner_Service": "Chassis Services",
    "Source": "CAN Gateway",
    "Dashboard": "N",
    "UVI_Companion": "Y",
    "Episode_Used": "Y",
    "Description": "Frequent corrections"
  },
  {
    "Domain": "Chassis.ADAS",
    "KUKSA_Path": "Vehicle.Suspension.Mode",
    "Type": "string",
    "Unit": "",
    "Owner_Service": "Chassis Services",
    "Source": "CAN Gateway",
    "Dashboard": "Y",
    "UVI_Companion": "Y",
    "Episode_Used": "Y",
    "Description": "Suspension mode"
  },
  {
    "Domain": "Chassis.ADAS",
    "KUKSA_Path": "Vehicle.Suspension.Health",
    "Type": "string",
    "Unit": "",
    "Owner_Service": "Chassis Services",
    "Source": "CAN Gateway",
    "Dashboard": "Y",
    "UVI_Companion": "Y",
    "Episode_Used": "Y",
    "Description": "Suspension health"
  },
  {
    "Domain": "Chassis.ADAS",
    "KUKSA_Path": "Vehicle.Tires.FL.Pressure",
    "Type": "float",
    "Unit": "psi",
    "Owner_Service": "Chassis Services",
    "Source": "CAN Gateway",
    "Dashboard": "Y",
    "UVI_Companion": "Y",
    "Episode_Used": "Y",
    "Description": "Front-left pressure"
  },
  {
    "Domain": "Chassis.ADAS",
    "KUKSA_Path": "Vehicle.Tires.FR.Pressure",
    "Type": "float",
    "Unit": "psi",
    "Owner_Service": "Chassis Services",
    "Source": "CAN Gateway",
    "Dashboard": "Y",
    "UVI_Companion": "Y",
    "Episode_Used": "Y",
    "Description": "Front-right pressure"
  },
  {
    "Domain": "Chassis.ADAS",
    "KUKSA_Path": "Vehicle.Tires.RL.Pressure",
    "Type": "float",
    "Unit": "psi",
    "Owner_Service": "Chassis Services",
    "Source": "CAN Gateway",
    "Dashboard": "Y",
    "UVI_Companion": "Y",
    "Episode_Used": "Y",
    "Description": "Rear-left pressure"
  },
  {
    "Domain": "Chassis.ADAS",
    "KUKSA_Path": "Vehicle.Tires.RR.Pressure",
    "Type": "float",
    "Unit": "psi",
    "Owner_Service": "Chassis Services",
    "Source": "CAN Gateway",
    "Dashboard": "Y",
    "UVI_Companion": "Y",
    "Episode_Used": "Y",
    "Description": "Rear-right pressure"
  },
  {
    "Domain": "Chassis.ADAS",
    "KUKSA_Path": "Vehicle.Tires.FL.Temperature",
    "Type": "float",
    "Unit": "C",
    "Owner_Service": "Chassis Services",
    "Source": "CAN Gateway",
    "Dashboard": "Y",
    "UVI_Companion": "Y",
    "Episode_Used": "Y",
    "Description": "Front-left tire temp"
  },
  {
    "Domain": "Chassis.ADAS",
    "KUKSA_Path": "Vehicle.Tires.LowPressureWarning",
    "Type": "boolean",
    "Unit": "",
    "Owner_Service": "Chassis Services",
    "Source": "CAN Gateway",
    "Dashboard": "Y",
    "UVI_Companion": "Y",
    "Episode_Used": "Y",
    "Description": "Low pressure warning"
  },
  {
    "Domain": "Chassis.ADAS",
    "KUKSA_Path": "Vehicle.Tires.PunctureRisk",
    "Type": "boolean",
    "Unit": "",
    "Owner_Service": "Chassis Services",
    "Source": "CAN Gateway",
    "Dashboard": "Y",
    "UVI_Companion": "Y",
    "Episode_Used": "Y",
    "Description": "Puncture risk"
  },
  {
    "Domain": "Chassis.ADAS",
    "KUKSA_Path": "Vehicle.ADAS.LaneAssistActive",
    "Type": "boolean",
    "Unit": "",
    "Owner_Service": "ADAS Services",
    "Source": "CAN Gateway",
    "Dashboard": "Y",
    "UVI_Companion": "Y",
    "Episode_Used": "Y",
    "Description": "Lane assist active"
  },
  {
    "Domain": "Chassis.ADAS",
    "KUKSA_Path": "Vehicle.ADAS.LaneDepartureWarning",
    "Type": "boolean",
    "Unit": "",
    "Owner_Service": "ADAS Services",
    "Source": "CAN Gateway",
    "Dashboard": "Y",
    "UVI_Companion": "Y",
    "Episode_Used": "Y",
    "Description": "Lane warning"
  },
  {
    "Domain": "Chassis.ADAS",
    "KUKSA_Path": "Vehicle.ADAS.AdaptiveCruiseActive",
    "Type": "boolean",
    "Unit": "",
    "Owner_Service": "ADAS Services",
    "Source": "CAN Gateway",
    "Dashboard": "Y",
    "UVI_Companion": "Y",
    "Episode_Used": "Y",
    "Description": "ACC active"
  },
  {
    "Domain": "Chassis.ADAS",
    "KUKSA_Path": "Vehicle.ADAS.BlindSpotAlert",
    "Type": "boolean",
    "Unit": "",
    "Owner_Service": "ADAS Services",
    "Source": "CAN Gateway",
    "Dashboard": "Y",
    "UVI_Companion": "Y",
    "Episode_Used": "Y",
    "Description": "Blind spot alert"
  },
  {
    "Domain": "Chassis.ADAS",
    "KUKSA_Path": "Vehicle.ADAS.ForwardCollisionRisk",
    "Type": "string",
    "Unit": "",
    "Owner_Service": "ADAS Services",
    "Source": "CAN Gateway",
    "Dashboard": "Y",
    "UVI_Companion": "Y",
    "Episode_Used": "Y",
    "Description": "Collision risk"
  },
  {
    "Domain": "Chassis.ADAS",
    "KUKSA_Path": "Vehicle.ADAS.PedestrianRisk",
    "Type": "boolean",
    "Unit": "",
    "Owner_Service": "ADAS Services",
    "Source": "CAN Gateway",
    "Dashboard": "Y",
    "UVI_Companion": "Y",
    "Episode_Used": "Y",
    "Description": "Pedestrian risk"
  },
  {
    "Domain": "Chassis.ADAS",
    "KUKSA_Path": "Vehicle.ADAS.SpeedLimit",
    "Type": "integer",
    "Unit": "km/h",
    "Owner_Service": "ADAS Services",
    "Source": "Map/Camera",
    "Dashboard": "Y",
    "UVI_Companion": "Y",
    "Episode_Used": "Y",
    "Description": "Detected speed limit"
  },
  {
    "Domain": "Chassis.ADAS",
    "KUKSA_Path": "Vehicle.ADAS.SpeedLimitExceeded",
    "Type": "boolean",
    "Unit": "",
    "Owner_Service": "ADAS Services",
    "Source": "Map/Camera",
    "Dashboard": "Y",
    "UVI_Companion": "Y",
    "Episode_Used": "Y",
    "Description": "Speed exceeded"
  },
  {
    "Domain": "Chassis.ADAS",
    "KUKSA_Path": "Vehicle.ADAS.SchoolZoneAhead",
    "Type": "boolean",
    "Unit": "",
    "Owner_Service": "ADAS Services",
    "Source": "Map",
    "Dashboard": "Y",
    "UVI_Companion": "Y",
    "Episode_Used": "Y",
    "Description": "School zone"
  },
  {
    "Domain": "Chassis.ADAS",
    "KUKSA_Path": "Vehicle.ADAS.ComplexJunctionAhead",
    "Type": "boolean",
    "Unit": "",
    "Owner_Service": "ADAS Services",
    "Source": "Map",
    "Dashboard": "Y",
    "UVI_Companion": "Y",
    "Episode_Used": "Y",
    "Description": "Complex junction ahead"
  },
  {
    "Domain": "Chassis.ADAS",
    "KUKSA_Path": "Vehicle.ADAS.CameraStatus",
    "Type": "string",
    "Unit": "",
    "Owner_Service": "ADAS Services",
    "Source": "CAN Gateway",
    "Dashboard": "Y",
    "UVI_Companion": "Y",
    "Episode_Used": "Y",
    "Description": "Camera status"
  },
  {
    "Domain": "Chassis.ADAS",
    "KUKSA_Path": "Vehicle.ADAS.RadarStatus",
    "Type": "string",
    "Unit": "",
    "Owner_Service": "ADAS Services",
    "Source": "CAN Gateway",
    "Dashboard": "Y",
    "UVI_Companion": "Y",
    "Episode_Used": "Y",
    "Description": "Radar status"
  },
  {
    "Domain": "Chassis.ADAS",
    "KUKSA_Path": "Vehicle.ADAS.SensorBlocked",
    "Type": "boolean",
    "Unit": "",
    "Owner_Service": "ADAS Services",
    "Source": "CAN Gateway",
    "Dashboard": "Y",
    "UVI_Companion": "Y",
    "Episode_Used": "Y",
    "Description": "Sensor blockage"
  },
  {
    "Domain": "Chassis.ADAS",
    "KUKSA_Path": "Vehicle.ADAS.CameraConfidence",
    "Type": "float",
    "Unit": "score",
    "Owner_Service": "ADAS Services",
    "Source": "CAN Gateway",
    "Dashboard": "Y",
    "UVI_Companion": "Y",
    "Episode_Used": "Y",
    "Description": "Camera confidence"
  },
  {
    "Domain": "Chassis.ADAS",
    "KUKSA_Path": "Vehicle.ADAS.RadarConfidence",
    "Type": "float",
    "Unit": "score",
    "Owner_Service": "ADAS Services",
    "Source": "CAN Gateway",
    "Dashboard": "Y",
    "UVI_Companion": "Y",
    "Episode_Used": "Y",
    "Description": "Radar confidence"
  },
  {
    "Domain": "Body.Cabin",
    "KUKSA_Path": "Vehicle.Body.DriverDoorOpen",
    "Type": "boolean",
    "Unit": "",
    "Owner_Service": "Body Services",
    "Source": "CAN Gateway",
    "Dashboard": "Y",
    "UVI_Companion": "Y",
    "Episode_Used": "Y",
    "Description": "Driver door open"
  },
  {
    "Domain": "Body.Cabin",
    "KUKSA_Path": "Vehicle.Body.PassengerDoorOpen",
    "Type": "boolean",
    "Unit": "",
    "Owner_Service": "Body Services",
    "Source": "CAN Gateway",
    "Dashboard": "Y",
    "UVI_Companion": "Y",
    "Episode_Used": "Y",
    "Description": "Passenger door open"
  },
  {
    "Domain": "Body.Cabin",
    "KUKSA_Path": "Vehicle.Body.RearLeftDoorOpen",
    "Type": "boolean",
    "Unit": "",
    "Owner_Service": "Body Services",
    "Source": "CAN Gateway",
    "Dashboard": "Y",
    "UVI_Companion": "Y",
    "Episode_Used": "Y",
    "Description": "Rear-left door open"
  },
  {
    "Domain": "Body.Cabin",
    "KUKSA_Path": "Vehicle.Body.RearRightDoorOpen",
    "Type": "boolean",
    "Unit": "",
    "Owner_Service": "Body Services",
    "Source": "CAN Gateway",
    "Dashboard": "Y",
    "UVI_Companion": "Y",
    "Episode_Used": "Y",
    "Description": "Rear-right door open"
  },
  {
    "Domain": "Body.Cabin",
    "KUKSA_Path": "Vehicle.Body.TrunkOpen",
    "Type": "boolean",
    "Unit": "",
    "Owner_Service": "Body Services",
    "Source": "CAN Gateway",
    "Dashboard": "Y",
    "UVI_Companion": "Y",
    "Episode_Used": "Y",
    "Description": "Trunk open"
  },
  {
    "Domain": "Body.Cabin",
    "KUKSA_Path": "Vehicle.Windows.FL.Open",
    "Type": "boolean",
    "Unit": "",
    "Owner_Service": "Body Services",
    "Source": "CAN Gateway",
    "Dashboard": "Y",
    "UVI_Companion": "Y",
    "Episode_Used": "Y",
    "Description": "Front-left window open"
  },
  {
    "Domain": "Body.Cabin",
    "KUKSA_Path": "Vehicle.Windows.FR.Open",
    "Type": "boolean",
    "Unit": "",
    "Owner_Service": "Body Services",
    "Source": "CAN Gateway",
    "Dashboard": "Y",
    "UVI_Companion": "Y",
    "Episode_Used": "Y",
    "Description": "Front-right window open"
  },
  {
    "Domain": "Body.Cabin",
    "KUKSA_Path": "Vehicle.Windows.RL.Open",
    "Type": "boolean",
    "Unit": "",
    "Owner_Service": "Body Services",
    "Source": "CAN Gateway",
    "Dashboard": "Y",
    "UVI_Companion": "Y",
    "Episode_Used": "Y",
    "Description": "Rear-left window open"
  },
  {
    "Domain": "Body.Cabin",
    "KUKSA_Path": "Vehicle.Windows.RR.Open",
    "Type": "boolean",
    "Unit": "",
    "Owner_Service": "Body Services",
    "Source": "CAN Gateway",
    "Dashboard": "Y",
    "UVI_Companion": "Y",
    "Episode_Used": "Y",
    "Description": "Rear-right window open"
  },
  {
    "Domain": "Body.Cabin",
    "KUKSA_Path": "Vehicle.Windows.SunroofOpen",
    "Type": "boolean",
    "Unit": "",
    "Owner_Service": "Body Services",
    "Source": "CAN Gateway",
    "Dashboard": "Y",
    "UVI_Companion": "Y",
    "Episode_Used": "N",
    "Description": "Sunroof open"
  },
  {
    "Domain": "Body.Cabin",
    "KUKSA_Path": "Vehicle.Lighting.HeadlightsOn",
    "Type": "boolean",
    "Unit": "",
    "Owner_Service": "Body Services",
    "Source": "CAN Gateway",
    "Dashboard": "Y",
    "UVI_Companion": "Y",
    "Episode_Used": "Y",
    "Description": "Headlights"
  },
  {
    "Domain": "Body.Cabin",
    "KUKSA_Path": "Vehicle.Lighting.HighBeamOn",
    "Type": "boolean",
    "Unit": "",
    "Owner_Service": "Body Services",
    "Source": "CAN Gateway",
    "Dashboard": "Y",
    "UVI_Companion": "Y",
    "Episode_Used": "Y",
    "Description": "High beam"
  },
  {
    "Domain": "Body.Cabin",
    "KUKSA_Path": "Vehicle.Lighting.AmbientLightMode",
    "Type": "string",
    "Unit": "",
    "Owner_Service": "Body Services",
    "Source": "CAN Gateway",
    "Dashboard": "Y",
    "UVI_Companion": "Y",
    "Episode_Used": "Y",
    "Description": "Cabin ambient lighting"
  },
  {
    "Domain": "Body.Cabin",
    "KUKSA_Path": "Vehicle.Cabin.Temperature",
    "Type": "float",
    "Unit": "C",
    "Owner_Service": "Body Services",
    "Source": "CAN Gateway",
    "Dashboard": "Y",
    "UVI_Companion": "Y",
    "Episode_Used": "Y",
    "Description": "Cabin temp"
  },
  {
    "Domain": "Body.Cabin",
    "KUKSA_Path": "Vehicle.Cabin.RearTemperature",
    "Type": "float",
    "Unit": "C",
    "Owner_Service": "Body Services",
    "Source": "CAN Gateway",
    "Dashboard": "Y",
    "UVI_Companion": "Y",
    "Episode_Used": "Y",
    "Description": "Rear cabin temp"
  },
  {
    "Domain": "Body.Cabin",
    "KUKSA_Path": "Vehicle.Cabin.NoiseLevel",
    "Type": "string",
    "Unit": "",
    "Owner_Service": "Body Services",
    "Source": "CAN Gateway",
    "Dashboard": "Y",
    "UVI_Companion": "Y",
    "Episode_Used": "Y",
    "Description": "Cabin noise"
  },
  {
    "Domain": "Body.Cabin",
    "KUKSA_Path": "Vehicle.Cabin.SunExposure",
    "Type": "string",
    "Unit": "",
    "Owner_Service": "Body Services",
    "Source": "CAN Gateway",
    "Dashboard": "Y",
    "UVI_Companion": "Y",
    "Episode_Used": "Y",
    "Description": "Sun exposure"
  },
  {
    "Domain": "Body.Cabin",
    "KUKSA_Path": "Vehicle.Cabin.CalmEnvironmentActive",
    "Type": "boolean",
    "Unit": "",
    "Owner_Service": "Body Services",
    "Source": "CAN Gateway",
    "Dashboard": "Y",
    "UVI_Companion": "Y",
    "Episode_Used": "Y",
    "Description": "Calm mode active"
  },
  {
    "Domain": "Body.Cabin",
    "KUKSA_Path": "Vehicle.HVAC.FanSpeed",
    "Type": "integer",
    "Unit": "level",
    "Owner_Service": "Body Services",
    "Source": "CAN Gateway",
    "Dashboard": "Y",
    "UVI_Companion": "Y",
    "Episode_Used": "Y",
    "Description": "HVAC fan speed"
  },
  {
    "Domain": "Body.Cabin",
    "KUKSA_Path": "Vehicle.HVAC.AutoModeActive",
    "Type": "boolean",
    "Unit": "",
    "Owner_Service": "Body Services",
    "Source": "CAN Gateway",
    "Dashboard": "Y",
    "UVI_Companion": "Y",
    "Episode_Used": "Y",
    "Description": "Auto HVAC"
  },
  {
    "Domain": "Body.Cabin",
    "KUKSA_Path": "Vehicle.HVAC.RecirculationActive",
    "Type": "boolean",
    "Unit": "",
    "Owner_Service": "Body Services",
    "Source": "CAN Gateway",
    "Dashboard": "Y",
    "UVI_Companion": "Y",
    "Episode_Used": "Y",
    "Description": "Recirculation"
  },
  {
    "Domain": "Body.Cabin",
    "KUKSA_Path": "Vehicle.HVAC.RearAirflowActive",
    "Type": "boolean",
    "Unit": "",
    "Owner_Service": "Body Services",
    "Source": "CAN Gateway",
    "Dashboard": "Y",
    "UVI_Companion": "Y",
    "Episode_Used": "Y",
    "Description": "Rear airflow"
  },
  {
    "Domain": "Body.Cabin",
    "KUKSA_Path": "Vehicle.HVAC.FreshAirRecommended",
    "Type": "boolean",
    "Unit": "",
    "Owner_Service": "Body Services",
    "Source": "Derived",
    "Dashboard": "Y",
    "UVI_Companion": "Y",
    "Episode_Used": "Y",
    "Description": "Fresh air suggested"
  },
  {
    "Domain": "Body.Cabin",
    "KUKSA_Path": "Vehicle.AirQuality.CabinCO2",
    "Type": "integer",
    "Unit": "ppm",
    "Owner_Service": "Body Services",
    "Source": "CAN Gateway",
    "Dashboard": "Y",
    "UVI_Companion": "Y",
    "Episode_Used": "Y",
    "Description": "Cabin CO2"
  },
  {
    "Domain": "Body.Cabin",
    "KUKSA_Path": "Vehicle.AirQuality.CabinAQI",
    "Type": "integer",
    "Unit": "index",
    "Owner_Service": "Body Services",
    "Source": "CAN Gateway",
    "Dashboard": "Y",
    "UVI_Companion": "Y",
    "Episode_Used": "Y",
    "Description": "Cabin AQI"
  },
  {
    "Domain": "Body.Cabin",
    "KUKSA_Path": "Vehicle.AirQuality.OutsideAQI",
    "Type": "integer",
    "Unit": "index",
    "Owner_Service": "Connectivity Services",
    "Source": "Cloud",
    "Dashboard": "Y",
    "UVI_Companion": "Y",
    "Episode_Used": "Y",
    "Description": "Outside AQI"
  },
  {
    "Domain": "Body.Cabin",
    "KUKSA_Path": "Vehicle.Occupancy.DriverPresent",
    "Type": "boolean",
    "Unit": "",
    "Owner_Service": "Body Services",
    "Source": "CAN Gateway",
    "Dashboard": "Y",
    "UVI_Companion": "Y",
    "Episode_Used": "Y",
    "Description": "Driver present"
  },
  {
    "Domain": "Body.Cabin",
    "KUKSA_Path": "Vehicle.Occupancy.FrontPassengerPresent",
    "Type": "boolean",
    "Unit": "",
    "Owner_Service": "Body Services",
    "Source": "CAN Gateway",
    "Dashboard": "Y",
    "UVI_Companion": "Y",
    "Episode_Used": "Y",
    "Description": "Front passenger"
  },
  {
    "Domain": "Body.Cabin",
    "KUKSA_Path": "Vehicle.Occupancy.RearLeftOccupied",
    "Type": "boolean",
    "Unit": "",
    "Owner_Service": "Body Services",
    "Source": "CAN Gateway",
    "Dashboard": "Y",
    "UVI_Companion": "Y",
    "Episode_Used": "Y",
    "Description": "Rear-left occupied"
  },
  {
    "Domain": "Body.Cabin",
    "KUKSA_Path": "Vehicle.Occupancy.RearRightOccupied",
    "Type": "boolean",
    "Unit": "",
    "Owner_Service": "Body Services",
    "Source": "CAN Gateway",
    "Dashboard": "Y",
    "UVI_Companion": "Y",
    "Episode_Used": "Y",
    "Description": "Rear-right occupied"
  },
  {
    "Domain": "Body.Cabin",
    "KUKSA_Path": "Vehicle.Occupancy.OccupantCount",
    "Type": "integer",
    "Unit": "count",
    "Owner_Service": "Body Services",
    "Source": "CAN Gateway",
    "Dashboard": "Y",
    "UVI_Companion": "Y",
    "Episode_Used": "Y",
    "Description": "Occupant count"
  },
  {
    "Domain": "Body.Cabin",
    "KUKSA_Path": "Vehicle.Occupancy.ChildDetected",
    "Type": "boolean",
    "Unit": "",
    "Owner_Service": "Body Services",
    "Source": "CAN Gateway",
    "Dashboard": "Y",
    "UVI_Companion": "Y",
    "Episode_Used": "Y",
    "Description": "Child detected"
  },
  {
    "Domain": "Body.Cabin",
    "KUKSA_Path": "Vehicle.Occupancy.ChildSeatOccupied",
    "Type": "boolean",
    "Unit": "",
    "Owner_Service": "Body Services",
    "Source": "CAN Gateway",
    "Dashboard": "Y",
    "UVI_Companion": "Y",
    "Episode_Used": "Y",
    "Description": "Child seat occupied"
  },
  {
    "Domain": "Body.Cabin",
    "KUKSA_Path": "Vehicle.Occupancy.PetDetected",
    "Type": "boolean",
    "Unit": "",
    "Owner_Service": "Body Services",
    "Source": "CAN Gateway",
    "Dashboard": "Y",
    "UVI_Companion": "Y",
    "Episode_Used": "Y",
    "Description": "Pet detected"
  },
  {
    "Domain": "Body.Cabin",
    "KUKSA_Path": "Vehicle.Occupancy.PassengerSleeping",
    "Type": "boolean",
    "Unit": "",
    "Owner_Service": "Body Services",
    "Source": "CAN Gateway",
    "Dashboard": "Y",
    "UVI_Companion": "Y",
    "Episode_Used": "Y",
    "Description": "Passenger sleeping"
  },
  {
    "Domain": "Body.Cabin",
    "KUKSA_Path": "Vehicle.Cargo.PhoneDetected",
    "Type": "boolean",
    "Unit": "",
    "Owner_Service": "Body Services",
    "Source": "CAN Gateway",
    "Dashboard": "Y",
    "UVI_Companion": "Y",
    "Episode_Used": "Y",
    "Description": "Phone detected"
  },
  {
    "Domain": "Body.Cabin",
    "KUKSA_Path": "Vehicle.Cargo.LaptopDetected",
    "Type": "boolean",
    "Unit": "",
    "Owner_Service": "Body Services",
    "Source": "CAN Gateway",
    "Dashboard": "Y",
    "UVI_Companion": "Y",
    "Episode_Used": "Y",
    "Description": "Laptop detected"
  },
  {
    "Domain": "Body.Cabin",
    "KUKSA_Path": "Vehicle.Cargo.BagDetected",
    "Type": "boolean",
    "Unit": "",
    "Owner_Service": "Body Services",
    "Source": "CAN Gateway",
    "Dashboard": "Y",
    "UVI_Companion": "Y",
    "Episode_Used": "Y",
    "Description": "Bag detected"
  },
  {
    "Domain": "Body.Cabin",
    "KUKSA_Path": "Vehicle.Cargo.WalletDetected",
    "Type": "boolean",
    "Unit": "",
    "Owner_Service": "Body Services",
    "Source": "CAN Gateway",
    "Dashboard": "N",
    "UVI_Companion": "Y",
    "Episode_Used": "Y",
    "Description": "Wallet detected"
  },
  {
    "Domain": "Body.Cabin",
    "KUKSA_Path": "Vehicle.Cargo.GroceriesDetected",
    "Type": "boolean",
    "Unit": "",
    "Owner_Service": "Body Services",
    "Source": "CAN Gateway",
    "Dashboard": "N",
    "UVI_Companion": "Y",
    "Episode_Used": "Y",
    "Description": "Groceries detected"
  },
  {
    "Domain": "Body.Cabin",
    "KUKSA_Path": "Vehicle.Cargo.UmbrellaDetected",
    "Type": "boolean",
    "Unit": "",
    "Owner_Service": "Body Services",
    "Source": "CAN Gateway",
    "Dashboard": "N",
    "UVI_Companion": "Y",
    "Episode_Used": "Y",
    "Description": "Umbrella detected"
  },
  {
    "Domain": "Body.Cabin",
    "KUKSA_Path": "Vehicle.Cargo.FrozenItemsDetected",
    "Type": "boolean",
    "Unit": "",
    "Owner_Service": "Body Services",
    "Source": "CAN Gateway",
    "Dashboard": "N",
    "UVI_Companion": "Y",
    "Episode_Used": "Y",
    "Description": "Frozen items"
  },
  {
    "Domain": "Driver.Journey.Context",
    "KUKSA_Path": "Vehicle.DriverMonitoring.DriverID",
    "Type": "string",
    "Unit": "",
    "Owner_Service": "Driver Monitoring Services",
    "Source": "DMS",
    "Dashboard": "N",
    "UVI_Companion": "Y",
    "Episode_Used": "Y",
    "Description": "Driver profile ID"
  },
  {
    "Domain": "Driver.Journey.Context",
    "KUKSA_Path": "Vehicle.DriverMonitoring.DriverName",
    "Type": "string",
    "Unit": "",
    "Owner_Service": "Driver Monitoring Services",
    "Source": "DMS/Profile",
    "Dashboard": "Y",
    "UVI_Companion": "Y",
    "Episode_Used": "Y",
    "Description": "Driver name"
  },
  {
    "Domain": "Driver.Journey.Context",
    "KUKSA_Path": "Vehicle.DriverMonitoring.FatigueScore",
    "Type": "float",
    "Unit": "score",
    "Owner_Service": "Driver Monitoring Services",
    "Source": "DMS",
    "Dashboard": "Y",
    "UVI_Companion": "Y",
    "Episode_Used": "Y",
    "Description": "Fatigue score"
  },
  {
    "Domain": "Driver.Journey.Context",
    "KUKSA_Path": "Vehicle.DriverMonitoring.StressScore",
    "Type": "float",
    "Unit": "score",
    "Owner_Service": "Driver Monitoring Services",
    "Source": "DMS",
    "Dashboard": "Y",
    "UVI_Companion": "Y",
    "Episode_Used": "Y",
    "Description": "Stress score"
  },
  {
    "Domain": "Driver.Journey.Context",
    "KUKSA_Path": "Vehicle.DriverMonitoring.AttentionScore",
    "Type": "float",
    "Unit": "score",
    "Owner_Service": "Driver Monitoring Services",
    "Source": "DMS",
    "Dashboard": "Y",
    "UVI_Companion": "Y",
    "Episode_Used": "Y",
    "Description": "Attention score"
  },
  {
    "Domain": "Driver.Journey.Context",
    "KUKSA_Path": "Vehicle.DriverMonitoring.HeartRate",
    "Type": "integer",
    "Unit": "bpm",
    "Owner_Service": "Driver Monitoring Services",
    "Source": "Wearable/DMS",
    "Dashboard": "Y",
    "UVI_Companion": "Y",
    "Episode_Used": "Y",
    "Description": "Heart rate"
  },
  {
    "Domain": "Driver.Journey.Context",
    "KUKSA_Path": "Vehicle.DriverMonitoring.DriverMood",
    "Type": "string",
    "Unit": "",
    "Owner_Service": "Driver Monitoring Services",
    "Source": "DMS/Voice",
    "Dashboard": "Y",
    "UVI_Companion": "Y",
    "Episode_Used": "Y",
    "Description": "Driver mood"
  },
  {
    "Domain": "Driver.Journey.Context",
    "KUKSA_Path": "Vehicle.DriverMonitoring.EyesOnRoad",
    "Type": "boolean",
    "Unit": "",
    "Owner_Service": "Driver Monitoring Services",
    "Source": "DMS",
    "Dashboard": "Y",
    "UVI_Companion": "Y",
    "Episode_Used": "Y",
    "Description": "Eyes on road"
  },
  {
    "Domain": "Driver.Journey.Context",
    "KUKSA_Path": "Vehicle.DriverMonitoring.HandsOnWheel",
    "Type": "boolean",
    "Unit": "",
    "Owner_Service": "Driver Monitoring Services",
    "Source": "DMS",
    "Dashboard": "Y",
    "UVI_Companion": "Y",
    "Episode_Used": "Y",
    "Description": "Hands on wheel"
  },
  {
    "Domain": "Driver.Journey.Context",
    "KUKSA_Path": "Vehicle.DriverMonitoring.ContinuousDrivingDuration",
    "Type": "integer",
    "Unit": "min",
    "Owner_Service": "Driver Monitoring Services",
    "Source": "DMS",
    "Dashboard": "Y",
    "UVI_Companion": "Y",
    "Episode_Used": "Y",
    "Description": "Continuous drive time"
  },
  {
    "Domain": "Driver.Journey.Context",
    "KUKSA_Path": "Vehicle.DriverBehavior.Style",
    "Type": "string",
    "Unit": "",
    "Owner_Service": "Driver Monitoring Services",
    "Source": "DMS/CAN",
    "Dashboard": "Y",
    "UVI_Companion": "Y",
    "Episode_Used": "Y",
    "Description": "Driving style"
  },
  {
    "Domain": "Driver.Journey.Context",
    "KUKSA_Path": "Vehicle.DriverBehavior.SmoothnessScore",
    "Type": "float",
    "Unit": "score",
    "Owner_Service": "Driver Monitoring Services",
    "Source": "DMS/CAN",
    "Dashboard": "Y",
    "UVI_Companion": "Y",
    "Episode_Used": "Y",
    "Description": "Smoothness score"
  },
  {
    "Domain": "Driver.Journey.Context",
    "KUKSA_Path": "Vehicle.DriverBehavior.RapidAccelerationCount",
    "Type": "integer",
    "Unit": "count",
    "Owner_Service": "Driver Monitoring Services",
    "Source": "CAN Gateway",
    "Dashboard": "Y",
    "UVI_Companion": "Y",
    "Episode_Used": "Y",
    "Description": "Rapid acceleration"
  },
  {
    "Domain": "Driver.Journey.Context",
    "KUKSA_Path": "Vehicle.DriverBehavior.FrequentLaneChanges",
    "Type": "boolean",
    "Unit": "",
    "Owner_Service": "Driver Monitoring Services",
    "Source": "CAN Gateway",
    "Dashboard": "Y",
    "UVI_Companion": "Y",
    "Episode_Used": "Y",
    "Description": "Lane change pattern"
  },
  {
    "Domain": "Driver.Journey.Context",
    "KUKSA_Path": "Vehicle.Infotainment.MusicPlaying",
    "Type": "boolean",
    "Unit": "",
    "Owner_Service": "Infotainment Services",
    "Source": "Infotainment",
    "Dashboard": "Y",
    "UVI_Companion": "Y",
    "Episode_Used": "Y",
    "Description": "Music state"
  },
  {
    "Domain": "Driver.Journey.Context",
    "KUKSA_Path": "Vehicle.Infotainment.CurrentPlaylist",
    "Type": "string",
    "Unit": "",
    "Owner_Service": "Infotainment Services",
    "Source": "Infotainment",
    "Dashboard": "Y",
    "UVI_Companion": "Y",
    "Episode_Used": "Y",
    "Description": "Current playlist"
  },
  {
    "Domain": "Driver.Journey.Context",
    "KUKSA_Path": "Vehicle.Infotainment.PreferredPlaylist",
    "Type": "string",
    "Unit": "",
    "Owner_Service": "Infotainment Services",
    "Source": "Profile",
    "Dashboard": "Y",
    "UVI_Companion": "Y",
    "Episode_Used": "Y",
    "Description": "Preferred playlist"
  },
  {
    "Domain": "Driver.Journey.Context",
    "KUKSA_Path": "Vehicle.Infotainment.CallActive",
    "Type": "boolean",
    "Unit": "",
    "Owner_Service": "Infotainment Services",
    "Source": "Infotainment",
    "Dashboard": "Y",
    "UVI_Companion": "Y",
    "Episode_Used": "Y",
    "Description": "Call active"
  },
  {
    "Domain": "Driver.Journey.Context",
    "KUKSA_Path": "Vehicle.Infotainment.VolumeLevel",
    "Type": "integer",
    "Unit": "level",
    "Owner_Service": "Infotainment Services",
    "Source": "Infotainment",
    "Dashboard": "Y",
    "UVI_Companion": "Y",
    "Episode_Used": "Y",
    "Description": "Volume level"
  },
  {
    "Domain": "Driver.Journey.Context",
    "KUKSA_Path": "Vehicle.Voice.MicrophoneActive",
    "Type": "boolean",
    "Unit": "",
    "Owner_Service": "Infotainment Services",
    "Source": "Voice",
    "Dashboard": "Y",
    "UVI_Companion": "Y",
    "Episode_Used": "Y",
    "Description": "Microphone state"
  },
  {
    "Domain": "Driver.Journey.Context",
    "KUKSA_Path": "Vehicle.Voice.LastDriverInputText",
    "Type": "string",
    "Unit": "",
    "Owner_Service": "Infotainment Services",
    "Source": "Voice/STT",
    "Dashboard": "N",
    "UVI_Companion": "Y",
    "Episode_Used": "Y",
    "Description": "Last driver utterance text"
  },
  {
    "Domain": "Driver.Journey.Context",
    "KUKSA_Path": "Vehicle.Voice.LastDriverIntent",
    "Type": "string",
    "Unit": "",
    "Owner_Service": "Infotainment Services",
    "Source": "NLU",
    "Dashboard": "N",
    "UVI_Companion": "Y",
    "Episode_Used": "Y",
    "Description": "Parsed driver intent"
  },
  {
    "Domain": "Driver.Journey.Context",
    "KUKSA_Path": "Vehicle.Voice.LastDriverSentiment",
    "Type": "string",
    "Unit": "",
    "Owner_Service": "Infotainment Services",
    "Source": "NLU",
    "Dashboard": "N",
    "UVI_Companion": "Y",
    "Episode_Used": "Y",
    "Description": "Driver sentiment"
  },
  {
    "Domain": "Driver.Journey.Context",
    "KUKSA_Path": "Vehicle.Voice.LastDriverUrgency",
    "Type": "string",
    "Unit": "",
    "Owner_Service": "Infotainment Services",
    "Source": "NLU",
    "Dashboard": "N",
    "UVI_Companion": "Y",
    "Episode_Used": "Y",
    "Description": "Urgency in driver speech"
  },
  {
    "Domain": "Driver.Journey.Context",
    "KUKSA_Path": "Vehicle.Voice.LastDriverPreferenceUpdate",
    "Type": "string",
    "Unit": "",
    "Owner_Service": "Infotainment Services",
    "Source": "NLU",
    "Dashboard": "N",
    "UVI_Companion": "Y",
    "Episode_Used": "Y",
    "Description": "Preference learned from speech"
  },
  {
    "Domain": "Driver.Journey.Context",
    "KUKSA_Path": "Vehicle.Voice.DriverQuestionActive",
    "Type": "boolean",
    "Unit": "",
    "Owner_Service": "Infotainment Services",
    "Source": "Voice",
    "Dashboard": "Y",
    "UVI_Companion": "Y",
    "Episode_Used": "Y",
    "Description": "Driver asked question"
  },
  {
    "Domain": "Driver.Journey.Context",
    "KUKSA_Path": "Vehicle.Voice.SpeechConfidence",
    "Type": "float",
    "Unit": "score",
    "Owner_Service": "Infotainment Services",
    "Source": "STT",
    "Dashboard": "N",
    "UVI_Companion": "Y",
    "Episode_Used": "Y",
    "Description": "STT confidence"
  },
  {
    "Domain": "Driver.Journey.Context",
    "KUKSA_Path": "Vehicle.Voice.CompanionCurrentlySpeaking",
    "Type": "boolean",
    "Unit": "",
    "Owner_Service": "UVI Companion Services",
    "Source": "UVI",
    "Dashboard": "Y",
    "UVI_Companion": "Y",
    "Episode_Used": "Y",
    "Description": "Companion speaking"
  },
  {
    "Domain": "Driver.Journey.Context",
    "KUKSA_Path": "Vehicle.Voice.ConversationTurnId",
    "Type": "string",
    "Unit": "",
    "Owner_Service": "UVI Companion Services",
    "Source": "UVI",
    "Dashboard": "N",
    "UVI_Companion": "Y",
    "Episode_Used": "Y",
    "Description": "Conversation turn ID"
  },
  {
    "Domain": "Driver.Journey.Context",
    "KUKSA_Path": "Vehicle.Navigation.Destination",
    "Type": "string",
    "Unit": "",
    "Owner_Service": "Connectivity Services",
    "Source": "Navigation",
    "Dashboard": "Y",
    "UVI_Companion": "Y",
    "Episode_Used": "Y",
    "Description": "Destination"
  },
  {
    "Domain": "Driver.Journey.Context",
    "KUKSA_Path": "Vehicle.Navigation.DestinationCategory",
    "Type": "string",
    "Unit": "",
    "Owner_Service": "Connectivity Services",
    "Source": "Navigation",
    "Dashboard": "Y",
    "UVI_Companion": "Y",
    "Episode_Used": "Y",
    "Description": "Destination type"
  },
  {
    "Domain": "Driver.Journey.Context",
    "KUKSA_Path": "Vehicle.Navigation.ETA",
    "Type": "integer",
    "Unit": "min",
    "Owner_Service": "Connectivity Services",
    "Source": "Navigation",
    "Dashboard": "Y",
    "UVI_Companion": "Y",
    "Episode_Used": "Y",
    "Description": "ETA"
  },
  {
    "Domain": "Driver.Journey.Context",
    "KUKSA_Path": "Vehicle.Navigation.DistanceRemaining",
    "Type": "float",
    "Unit": "km",
    "Owner_Service": "Connectivity Services",
    "Source": "Navigation",
    "Dashboard": "Y",
    "UVI_Companion": "Y",
    "Episode_Used": "Y",
    "Description": "Distance remaining"
  },
  {
    "Domain": "Driver.Journey.Context",
    "KUKSA_Path": "Vehicle.Navigation.RouteType",
    "Type": "string",
    "Unit": "",
    "Owner_Service": "Connectivity Services",
    "Source": "Navigation",
    "Dashboard": "Y",
    "UVI_Companion": "Y",
    "Episode_Used": "Y",
    "Description": "Route type"
  },
  {
    "Domain": "Driver.Journey.Context",
    "KUKSA_Path": "Vehicle.Navigation.AlternativeRouteAvailable",
    "Type": "boolean",
    "Unit": "",
    "Owner_Service": "Connectivity Services",
    "Source": "Navigation",
    "Dashboard": "Y",
    "UVI_Companion": "Y",
    "Episode_Used": "Y",
    "Description": "Alternate route"
  },
  {
    "Domain": "Driver.Journey.Context",
    "KUKSA_Path": "Vehicle.Navigation.ScenicRouteAvailable",
    "Type": "boolean",
    "Unit": "",
    "Owner_Service": "Connectivity Services",
    "Source": "Navigation",
    "Dashboard": "Y",
    "UVI_Companion": "Y",
    "Episode_Used": "Y",
    "Description": "Scenic route"
  },
  {
    "Domain": "Driver.Journey.Context",
    "KUKSA_Path": "Vehicle.Navigation.WrongDestinationDetected",
    "Type": "boolean",
    "Unit": "",
    "Owner_Service": "Connectivity Services",
    "Source": "Calendar/Nav",
    "Dashboard": "Y",
    "UVI_Companion": "Y",
    "Episode_Used": "Y",
    "Description": "Calendar/nav mismatch"
  },
  {
    "Domain": "Driver.Journey.Context",
    "KUKSA_Path": "Vehicle.Traffic.Level",
    "Type": "string",
    "Unit": "",
    "Owner_Service": "Connectivity Services",
    "Source": "Cloud",
    "Dashboard": "Y",
    "UVI_Companion": "Y",
    "Episode_Used": "Y",
    "Description": "Traffic level"
  },
  {
    "Domain": "Driver.Journey.Context",
    "KUKSA_Path": "Vehicle.Traffic.Increasing",
    "Type": "boolean",
    "Unit": "",
    "Owner_Service": "Connectivity Services",
    "Source": "Cloud",
    "Dashboard": "Y",
    "UVI_Companion": "Y",
    "Episode_Used": "Y",
    "Description": "Traffic increasing"
  },
  {
    "Domain": "Driver.Journey.Context",
    "KUKSA_Path": "Vehicle.Traffic.AccidentAhead",
    "Type": "boolean",
    "Unit": "",
    "Owner_Service": "Connectivity Services",
    "Source": "Cloud",
    "Dashboard": "Y",
    "UVI_Companion": "Y",
    "Episode_Used": "Y",
    "Description": "Accident ahead"
  },
  {
    "Domain": "Driver.Journey.Context",
    "KUKSA_Path": "Vehicle.Traffic.RoadClosureAhead",
    "Type": "boolean",
    "Unit": "",
    "Owner_Service": "Connectivity Services",
    "Source": "Cloud",
    "Dashboard": "Y",
    "UVI_Companion": "Y",
    "Episode_Used": "Y",
    "Description": "Road closure"
  },
  {
    "Domain": "Driver.Journey.Context",
    "KUKSA_Path": "Vehicle.Weather.Current",
    "Type": "string",
    "Unit": "",
    "Owner_Service": "Connectivity Services",
    "Source": "Cloud/Sensor",
    "Dashboard": "Y",
    "UVI_Companion": "Y",
    "Episode_Used": "Y",
    "Description": "Current weather"
  },
  {
    "Domain": "Driver.Journey.Context",
    "KUKSA_Path": "Vehicle.Weather.Ahead",
    "Type": "string",
    "Unit": "",
    "Owner_Service": "Connectivity Services",
    "Source": "Cloud",
    "Dashboard": "Y",
    "UVI_Companion": "Y",
    "Episode_Used": "Y",
    "Description": "Weather ahead"
  },
  {
    "Domain": "Driver.Journey.Context",
    "KUKSA_Path": "Vehicle.Weather.RainExpected",
    "Type": "boolean",
    "Unit": "",
    "Owner_Service": "Connectivity Services",
    "Source": "Cloud",
    "Dashboard": "Y",
    "UVI_Companion": "Y",
    "Episode_Used": "Y",
    "Description": "Rain expected"
  },
  {
    "Domain": "Driver.Journey.Context",
    "KUKSA_Path": "Vehicle.Weather.RainExpectedInMinutes",
    "Type": "integer",
    "Unit": "min",
    "Owner_Service": "Connectivity Services",
    "Source": "Cloud",
    "Dashboard": "Y",
    "UVI_Companion": "Y",
    "Episode_Used": "Y",
    "Description": "Rain ETA"
  },
  {
    "Domain": "Driver.Journey.Context",
    "KUKSA_Path": "Vehicle.Weather.Visibility",
    "Type": "integer",
    "Unit": "%",
    "Owner_Service": "Connectivity Services",
    "Source": "Cloud/Sensor",
    "Dashboard": "Y",
    "UVI_Companion": "Y",
    "Episode_Used": "Y",
    "Description": "Visibility"
  },
  {
    "Domain": "Driver.Journey.Context",
    "KUKSA_Path": "Vehicle.Weather.HailWarning",
    "Type": "boolean",
    "Unit": "",
    "Owner_Service": "Connectivity Services",
    "Source": "Cloud",
    "Dashboard": "Y",
    "UVI_Companion": "Y",
    "Episode_Used": "Y",
    "Description": "Hail warning"
  },
  {
    "Domain": "Driver.Journey.Context",
    "KUKSA_Path": "Vehicle.Weather.SunGlareExpected",
    "Type": "boolean",
    "Unit": "",
    "Owner_Service": "Connectivity Services",
    "Source": "Cloud/Map",
    "Dashboard": "Y",
    "UVI_Companion": "Y",
    "Episode_Used": "Y",
    "Description": "Sun glare"
  },
  {
    "Domain": "Driver.Journey.Context",
    "KUKSA_Path": "Vehicle.Calendar.NextEventTitle",
    "Type": "string",
    "Unit": "",
    "Owner_Service": "Connectivity Services",
    "Source": "Calendar",
    "Dashboard": "Y",
    "UVI_Companion": "Y",
    "Episode_Used": "Y",
    "Description": "Next event"
  },
  {
    "Domain": "Driver.Journey.Context",
    "KUKSA_Path": "Vehicle.Calendar.NextEventTime",
    "Type": "string",
    "Unit": "",
    "Owner_Service": "Connectivity Services",
    "Source": "Calendar",
    "Dashboard": "Y",
    "UVI_Companion": "Y",
    "Episode_Used": "Y",
    "Description": "Next event time"
  },
  {
    "Domain": "Driver.Journey.Context",
    "KUKSA_Path": "Vehicle.Calendar.NextEventLocation",
    "Type": "string",
    "Unit": "",
    "Owner_Service": "Connectivity Services",
    "Source": "Calendar",
    "Dashboard": "N",
    "UVI_Companion": "Y",
    "Episode_Used": "Y",
    "Description": "Next event location"
  },
  {
    "Domain": "Driver.Journey.Context",
    "KUKSA_Path": "Vehicle.Calendar.MeetingCompleted",
    "Type": "boolean",
    "Unit": "",
    "Owner_Service": "Connectivity Services",
    "Source": "Calendar",
    "Dashboard": "Y",
    "UVI_Companion": "Y",
    "Episode_Used": "Y",
    "Description": "Meeting completed"
  },
  {
    "Domain": "Driver.Journey.Context",
    "KUKSA_Path": "Vehicle.Calendar.InterviewScheduled",
    "Type": "boolean",
    "Unit": "",
    "Owner_Service": "Connectivity Services",
    "Source": "Calendar",
    "Dashboard": "Y",
    "UVI_Companion": "Y",
    "Episode_Used": "Y",
    "Description": "Interview scheduled"
  },
  {
    "Domain": "Driver.Journey.Context",
    "KUKSA_Path": "Vehicle.Calendar.PresentationTomorrow",
    "Type": "boolean",
    "Unit": "",
    "Owner_Service": "Connectivity Services",
    "Source": "Calendar",
    "Dashboard": "Y",
    "UVI_Companion": "Y",
    "Episode_Used": "Y",
    "Description": "Presentation tomorrow"
  },
  {
    "Domain": "Driver.Journey.Context",
    "KUKSA_Path": "Vehicle.Calendar.SchoolPickupTime",
    "Type": "string",
    "Unit": "",
    "Owner_Service": "Connectivity Services",
    "Source": "Calendar",
    "Dashboard": "Y",
    "UVI_Companion": "Y",
    "Episode_Used": "Y",
    "Description": "School pickup"
  },
  {
    "Domain": "Driver.Journey.Context",
    "KUKSA_Path": "Vehicle.Personalization.FavoriteCoffeeBrand",
    "Type": "string",
    "Unit": "",
    "Owner_Service": "Connectivity Services",
    "Source": "Profile",
    "Dashboard": "N",
    "UVI_Companion": "Y",
    "Episode_Used": "Y",
    "Description": "Favorite coffee brand"
  },
  {
    "Domain": "Driver.Journey.Context",
    "KUKSA_Path": "Vehicle.Personalization.FavoriteDrink",
    "Type": "string",
    "Unit": "",
    "Owner_Service": "Connectivity Services",
    "Source": "Profile",
    "Dashboard": "N",
    "UVI_Companion": "Y",
    "Episode_Used": "Y",
    "Description": "Favorite drink"
  },
  {
    "Domain": "Driver.Journey.Context",
    "KUKSA_Path": "Vehicle.Personalization.FavoriteGym",
    "Type": "string",
    "Unit": "",
    "Owner_Service": "Connectivity Services",
    "Source": "Profile",
    "Dashboard": "N",
    "UVI_Companion": "Y",
    "Episode_Used": "Y",
    "Description": "Favorite gym"
  },
  {
    "Domain": "Driver.Journey.Context",
    "KUKSA_Path": "Vehicle.Personalization.MusicProfile",
    "Type": "string",
    "Unit": "",
    "Owner_Service": "Infotainment Services",
    "Source": "Profile",
    "Dashboard": "Y",
    "UVI_Companion": "Y",
    "Episode_Used": "Y",
    "Description": "Music profile"
  },
  {
    "Domain": "Driver.Journey.Context",
    "KUKSA_Path": "Vehicle.Personalization.LikesScenicRoutes",
    "Type": "boolean",
    "Unit": "",
    "Owner_Service": "Connectivity Services",
    "Source": "Profile",
    "Dashboard": "N",
    "UVI_Companion": "Y",
    "Episode_Used": "Y",
    "Description": "Scenic preference"
  },
  {
    "Domain": "Driver.Journey.Context",
    "KUKSA_Path": "Vehicle.Memory.RoutineDetected",
    "Type": "boolean",
    "Unit": "",
    "Owner_Service": "Connectivity Services",
    "Source": "Memory",
    "Dashboard": "N",
    "UVI_Companion": "Y",
    "Episode_Used": "Y",
    "Description": "Routine detected"
  },
  {
    "Domain": "Driver.Journey.Context",
    "KUKSA_Path": "Vehicle.Memory.HabitPattern",
    "Type": "string",
    "Unit": "",
    "Owner_Service": "Connectivity Services",
    "Source": "Memory",
    "Dashboard": "N",
    "UVI_Companion": "Y",
    "Episode_Used": "Y",
    "Description": "Detected habit"
  },
  {
    "Domain": "Driver.Journey.Context",
    "KUKSA_Path": "Vehicle.Memory.LifestylePattern",
    "Type": "string",
    "Unit": "",
    "Owner_Service": "Connectivity Services",
    "Source": "Memory",
    "Dashboard": "N",
    "UVI_Companion": "Y",
    "Episode_Used": "Y",
    "Description": "Lifestyle pattern"
  },
  {
    "Domain": "Driver.Journey.Context",
    "KUKSA_Path": "Vehicle.Memory.FrequentDestination",
    "Type": "string",
    "Unit": "",
    "Owner_Service": "Connectivity Services",
    "Source": "Memory",
    "Dashboard": "N",
    "UVI_Companion": "Y",
    "Episode_Used": "Y",
    "Description": "Frequent destination"
  },
  {
    "Domain": "Driver.Journey.Context",
    "KUKSA_Path": "Vehicle.FoodServices.CoffeeNearby",
    "Type": "boolean",
    "Unit": "",
    "Owner_Service": "Connectivity Services",
    "Source": "Cloud/POI",
    "Dashboard": "Y",
    "UVI_Companion": "Y",
    "Episode_Used": "Y",
    "Description": "Coffee nearby"
  },
  {
    "Domain": "Driver.Journey.Context",
    "KUKSA_Path": "Vehicle.FoodServices.CoffeeDistance",
    "Type": "float",
    "Unit": "km",
    "Owner_Service": "Connectivity Services",
    "Source": "Cloud/POI",
    "Dashboard": "Y",
    "UVI_Companion": "Y",
    "Episode_Used": "Y",
    "Description": "Coffee distance"
  },
  {
    "Domain": "Driver.Journey.Context",
    "KUKSA_Path": "Vehicle.FoodServices.FavoriteCoffeeNearby",
    "Type": "boolean",
    "Unit": "",
    "Owner_Service": "Connectivity Services",
    "Source": "Cloud/POI",
    "Dashboard": "Y",
    "UVI_Companion": "Y",
    "Episode_Used": "Y",
    "Description": "Favorite coffee"
  },
  {
    "Domain": "Driver.Journey.Context",
    "KUKSA_Path": "Vehicle.FoodServices.RestaurantNearby",
    "Type": "boolean",
    "Unit": "",
    "Owner_Service": "Connectivity Services",
    "Source": "Cloud/POI",
    "Dashboard": "Y",
    "UVI_Companion": "Y",
    "Episode_Used": "Y",
    "Description": "Restaurant nearby"
  },
  {
    "Domain": "Driver.Journey.Context",
    "KUKSA_Path": "Vehicle.ParkingServices.DestinationParkingAvailability",
    "Type": "string",
    "Unit": "",
    "Owner_Service": "Connectivity Services",
    "Source": "Cloud/POI",
    "Dashboard": "Y",
    "UVI_Companion": "Y",
    "Episode_Used": "Y",
    "Description": "Parking availability"
  },
  {
    "Domain": "Driver.Journey.Context",
    "KUKSA_Path": "Vehicle.ParkingServices.AlternateParkingAvailable",
    "Type": "boolean",
    "Unit": "",
    "Owner_Service": "Connectivity Services",
    "Source": "Cloud/POI",
    "Dashboard": "Y",
    "UVI_Companion": "Y",
    "Episode_Used": "Y",
    "Description": "Alternate parking"
  },
  {
    "Domain": "Driver.Journey.Context",
    "KUKSA_Path": "Vehicle.TravelServices.FlightStatus",
    "Type": "string",
    "Unit": "",
    "Owner_Service": "Connectivity Services",
    "Source": "Cloud",
    "Dashboard": "Y",
    "UVI_Companion": "Y",
    "Episode_Used": "Y",
    "Description": "Flight status"
  },
  {
    "Domain": "Driver.Journey.Context",
    "KUKSA_Path": "Vehicle.TravelServices.FlightDelayMinutes",
    "Type": "integer",
    "Unit": "min",
    "Owner_Service": "Connectivity Services",
    "Source": "Cloud",
    "Dashboard": "Y",
    "UVI_Companion": "Y",
    "Episode_Used": "Y",
    "Description": "Flight delay"
  },
  {
    "Domain": "Driver.Journey.Context",
    "KUKSA_Path": "Vehicle.TravelServices.AirportTerminal",
    "Type": "string",
    "Unit": "",
    "Owner_Service": "Connectivity Services",
    "Source": "Cloud",
    "Dashboard": "Y",
    "UVI_Companion": "Y",
    "Episode_Used": "Y",
    "Description": "Airport terminal"
  },
  {
    "Domain": "Driver.Journey.Context",
    "KUKSA_Path": "Vehicle.TravelServices.SecurityWaitTime",
    "Type": "integer",
    "Unit": "min",
    "Owner_Service": "Connectivity Services",
    "Source": "Cloud",
    "Dashboard": "Y",
    "UVI_Companion": "Y",
    "Episode_Used": "Y",
    "Description": "Security wait"
  },
  {
    "Domain": "Health.Security.UVI",
    "KUKSA_Path": "Vehicle.Diagnostics.DTCActive",
    "Type": "boolean",
    "Unit": "",
    "Owner_Service": "Vehicle Health Services",
    "Source": "CAN Gateway",
    "Dashboard": "Y",
    "UVI_Companion": "Y",
    "Episode_Used": "Y",
    "Description": "DTC active"
  },
  {
    "Domain": "Health.Security.UVI",
    "KUKSA_Path": "Vehicle.Diagnostics.DTCCode",
    "Type": "string",
    "Unit": "",
    "Owner_Service": "Vehicle Health Services",
    "Source": "CAN Gateway",
    "Dashboard": "Y",
    "UVI_Companion": "Y",
    "Episode_Used": "Y",
    "Description": "DTC code"
  },
  {
    "Domain": "Health.Security.UVI",
    "KUKSA_Path": "Vehicle.Diagnostics.CriticalFault",
    "Type": "boolean",
    "Unit": "",
    "Owner_Service": "Vehicle Health Services",
    "Source": "CAN Gateway",
    "Dashboard": "Y",
    "UVI_Companion": "Y",
    "Episode_Used": "Y",
    "Description": "Critical fault"
  },
  {
    "Domain": "Health.Security.UVI",
    "KUKSA_Path": "Vehicle.Diagnostics.ServiceDueDistance",
    "Type": "integer",
    "Unit": "km",
    "Owner_Service": "Vehicle Health Services",
    "Source": "CAN Gateway",
    "Dashboard": "Y",
    "UVI_Companion": "Y",
    "Episode_Used": "Y",
    "Description": "Service due distance"
  },
  {
    "Domain": "Health.Security.UVI",
    "KUKSA_Path": "Vehicle.Diagnostics.BatteryWarning",
    "Type": "boolean",
    "Unit": "",
    "Owner_Service": "Vehicle Health Services",
    "Source": "CAN Gateway",
    "Dashboard": "Y",
    "UVI_Companion": "Y",
    "Episode_Used": "Y",
    "Description": "Battery warning"
  },
  {
    "Domain": "Health.Security.UVI",
    "KUKSA_Path": "Vehicle.Diagnostics.BrakeWarning",
    "Type": "boolean",
    "Unit": "",
    "Owner_Service": "Vehicle Health Services",
    "Source": "CAN Gateway",
    "Dashboard": "Y",
    "UVI_Companion": "Y",
    "Episode_Used": "Y",
    "Description": "Brake warning"
  },
  {
    "Domain": "Health.Security.UVI",
    "KUKSA_Path": "Vehicle.Diagnostics.TireWarning",
    "Type": "boolean",
    "Unit": "",
    "Owner_Service": "Vehicle Health Services",
    "Source": "CAN Gateway",
    "Dashboard": "Y",
    "UVI_Companion": "Y",
    "Episode_Used": "Y",
    "Description": "Tire warning"
  },
  {
    "Domain": "Health.Security.UVI",
    "KUKSA_Path": "Vehicle.Diagnostics.ThermalWarning",
    "Type": "boolean",
    "Unit": "",
    "Owner_Service": "Vehicle Health Services",
    "Source": "CAN Gateway",
    "Dashboard": "Y",
    "UVI_Companion": "Y",
    "Episode_Used": "Y",
    "Description": "Thermal warning"
  },
  {
    "Domain": "Health.Security.UVI",
    "KUKSA_Path": "Vehicle.Diagnostics.VehicleHealthStatus",
    "Type": "string",
    "Unit": "",
    "Owner_Service": "Vehicle Health Services",
    "Source": "CAN Gateway",
    "Dashboard": "Y",
    "UVI_Companion": "Y",
    "Episode_Used": "Y",
    "Description": "Vehicle health state"
  },
  {
    "Domain": "Health.Security.UVI",
    "KUKSA_Path": "Vehicle.Maintenance.ServiceDueSoon",
    "Type": "boolean",
    "Unit": "",
    "Owner_Service": "Vehicle Health Services",
    "Source": "Model",
    "Dashboard": "Y",
    "UVI_Companion": "Y",
    "Episode_Used": "Y",
    "Description": "Service due soon"
  },
  {
    "Domain": "Health.Security.UVI",
    "KUKSA_Path": "Vehicle.Maintenance.ServiceDueKm",
    "Type": "integer",
    "Unit": "km",
    "Owner_Service": "Vehicle Health Services",
    "Source": "Model",
    "Dashboard": "Y",
    "UVI_Companion": "Y",
    "Episode_Used": "Y",
    "Description": "Service due km"
  },
  {
    "Domain": "Health.Security.UVI",
    "KUKSA_Path": "Vehicle.Maintenance.PredictiveMaintenanceAlert",
    "Type": "boolean",
    "Unit": "",
    "Owner_Service": "Vehicle Health Services",
    "Source": "Model",
    "Dashboard": "Y",
    "UVI_Companion": "Y",
    "Episode_Used": "Y",
    "Description": "Predictive alert"
  },
  {
    "Domain": "Health.Security.UVI",
    "KUKSA_Path": "Vehicle.Security.DigitalKeyActive",
    "Type": "boolean",
    "Unit": "",
    "Owner_Service": "Connectivity Services",
    "Source": "Security",
    "Dashboard": "Y",
    "UVI_Companion": "Y",
    "Episode_Used": "Y",
    "Description": "Digital key active"
  },
  {
    "Domain": "Health.Security.UVI",
    "KUKSA_Path": "Vehicle.Security.AuthorizedUserPresent",
    "Type": "boolean",
    "Unit": "",
    "Owner_Service": "Connectivity Services",
    "Source": "Security",
    "Dashboard": "N",
    "UVI_Companion": "Y",
    "Episode_Used": "Y",
    "Description": "Authorized user"
  },
  {
    "Domain": "Health.Security.UVI",
    "KUKSA_Path": "Vehicle.Security.UnauthorizedAccessDetected",
    "Type": "boolean",
    "Unit": "",
    "Owner_Service": "Connectivity Services",
    "Source": "Security",
    "Dashboard": "Y",
    "UVI_Companion": "Y",
    "Episode_Used": "Y",
    "Description": "Unauthorized access"
  },
  {
    "Domain": "Health.Security.UVI",
    "KUKSA_Path": "Vehicle.Security.CyberThreatLevel",
    "Type": "string",
    "Unit": "",
    "Owner_Service": "Connectivity Services",
    "Source": "Security",
    "Dashboard": "Y",
    "UVI_Companion": "Y",
    "Episode_Used": "Y",
    "Description": "Cyber threat level"
  },
  {
    "Domain": "Health.Security.UVI",
    "KUKSA_Path": "Vehicle.Security.AccessControlAlert",
    "Type": "boolean",
    "Unit": "",
    "Owner_Service": "Connectivity Services",
    "Source": "Security",
    "Dashboard": "Y",
    "UVI_Companion": "Y",
    "Episode_Used": "Y",
    "Description": "Access alert"
  },
  {
    "Domain": "Health.Security.UVI",
    "KUKSA_Path": "Vehicle.Security.AccessControlLockdown",
    "Type": "boolean",
    "Unit": "",
    "Owner_Service": "Connectivity Services",
    "Source": "Security",
    "Dashboard": "Y",
    "UVI_Companion": "Y",
    "Episode_Used": "Y",
    "Description": "Lockdown"
  },
  {
    "Domain": "Health.Security.UVI",
    "KUKSA_Path": "Vehicle.Security.NetworkHealthStatus",
    "Type": "string",
    "Unit": "",
    "Owner_Service": "Connectivity Services",
    "Source": "Security",
    "Dashboard": "Y",
    "UVI_Companion": "Y",
    "Episode_Used": "Y",
    "Description": "Vehicle network health"
  },
  {
    "Domain": "Health.Security.UVI",
    "KUKSA_Path": "Vehicle.Security.SomeIPTrafficLevel",
    "Type": "string",
    "Unit": "",
    "Owner_Service": "Connectivity Services",
    "Source": "Security",
    "Dashboard": "N",
    "UVI_Companion": "Y",
    "Episode_Used": "Y",
    "Description": "SOME/IP traffic"
  },
  {
    "Domain": "Health.Security.UVI",
    "KUKSA_Path": "Vehicle.Security.SomeIPAnomalyDetected",
    "Type": "boolean",
    "Unit": "",
    "Owner_Service": "Connectivity Services",
    "Source": "Security",
    "Dashboard": "Y",
    "UVI_Companion": "Y",
    "Episode_Used": "Y",
    "Description": "SOME/IP anomaly"
  },
  {
    "Domain": "Health.Security.UVI",
    "KUKSA_Path": "Vehicle.UVI.ActiveEpisode",
    "Type": "string",
    "Unit": "",
    "Owner_Service": "UVI Companion Services",
    "Source": "Episode/Companion",
    "Dashboard": "Y",
    "UVI_Companion": "Y",
    "Episode_Used": "Y",
    "Description": "Currently active episode"
  },
  {
    "Domain": "Health.Security.UVI",
    "KUKSA_Path": "Vehicle.UVI.ActiveScenarioTags",
    "Type": "string[]",
    "Unit": "",
    "Owner_Service": "UVI Companion Services",
    "Source": "Episode/Companion",
    "Dashboard": "Y",
    "UVI_Companion": "Y",
    "Episode_Used": "Y",
    "Description": "Active scenario tags"
  },
  {
    "Domain": "Health.Security.UVI",
    "KUKSA_Path": "Vehicle.UVI.ContextCompletenessScore",
    "Type": "float",
    "Unit": "score",
    "Owner_Service": "UVI Companion Services",
    "Source": "UVI",
    "Dashboard": "N",
    "UVI_Companion": "Y",
    "Episode_Used": "Y",
    "Description": "Context completeness"
  },
  {
    "Domain": "Health.Security.UVI",
    "KUKSA_Path": "Vehicle.UVI.InsightPriority",
    "Type": "string",
    "Unit": "",
    "Owner_Service": "UVI Companion Services",
    "Source": "UVI",
    "Dashboard": "Y",
    "UVI_Companion": "Y",
    "Episode_Used": "Y",
    "Description": "Insight priority"
  },
  {
    "Domain": "Health.Security.UVI",
    "KUKSA_Path": "Vehicle.UVI.RecommendedTone",
    "Type": "string",
    "Unit": "",
    "Owner_Service": "UVI Companion Services",
    "Source": "UVI",
    "Dashboard": "N",
    "UVI_Companion": "Y",
    "Episode_Used": "Y",
    "Description": "Recommended tone"
  },
  {
    "Domain": "Health.Security.UVI",
    "KUKSA_Path": "Vehicle.UVI.CompanionMode",
    "Type": "string",
    "Unit": "",
    "Owner_Service": "UVI Companion Services",
    "Source": "UVI",
    "Dashboard": "Y",
    "UVI_Companion": "Y",
    "Episode_Used": "Y",
    "Description": "Companion mode"
  },
  {
    "Domain": "Health.Security.UVI",
    "KUKSA_Path": "Vehicle.UVI.LastInsight",
    "Type": "string",
    "Unit": "",
    "Owner_Service": "UVI Companion Services",
    "Source": "UVI",
    "Dashboard": "Y",
    "UVI_Companion": "Y",
    "Episode_Used": "Y",
    "Description": "Last insight"
  },
  {
    "Domain": "Health.Security.UVI",
    "KUKSA_Path": "Vehicle.UVI.LastCompanionMessage",
    "Type": "string",
    "Unit": "",
    "Owner_Service": "UVI Companion Services",
    "Source": "UVI",
    "Dashboard": "Y",
    "UVI_Companion": "Y",
    "Episode_Used": "Y",
    "Description": "Last spoken/displayed message"
  },
  {
    "Domain": "Health.Security.UVI",
    "KUKSA_Path": "Vehicle.UVI.LastDriverResponse",
    "Type": "string",
    "Unit": "",
    "Owner_Service": "UVI Companion Services",
    "Source": "Voice",
    "Dashboard": "N",
    "UVI_Companion": "Y",
    "Episode_Used": "Y",
    "Description": "Last driver response"
  },
  {
    "Domain": "Health.Security.UVI",
    "KUKSA_Path": "Vehicle.UVI.NextSuggestedAction",
    "Type": "string",
    "Unit": "",
    "Owner_Service": "UVI Companion Services",
    "Source": "UVI",
    "Dashboard": "Y",
    "UVI_Companion": "Y",
    "Episode_Used": "Y",
    "Description": "Next suggested action"
  },
  {
    "Domain": "Health.Security.UVI",
    "KUKSA_Path": "Vehicle.UVI.SpeakNowRecommended",
    "Type": "boolean",
    "Unit": "",
    "Owner_Service": "UVI Companion Services",
    "Source": "UVI",
    "Dashboard": "N",
    "UVI_Companion": "Y",
    "Episode_Used": "Y",
    "Description": "Speak now gate"
  },
  {
    "Domain": "Health.Security.UVI",
    "KUKSA_Path": "Vehicle.UVI.DisplayOnDashboard",
    "Type": "boolean",
    "Unit": "",
    "Owner_Service": "UVI Companion Services",
    "Source": "UVI",
    "Dashboard": "Y",
    "UVI_Companion": "Y",
    "Episode_Used": "Y",
    "Description": "Show message on dashboard"
  },
  {
    "Domain": "Health.Security.UVI",
    "KUKSA_Path": "Vehicle.UVI.RequiresDriverConfirmation",
    "Type": "boolean",
    "Unit": "",
    "Owner_Service": "UVI Companion Services",
    "Source": "UVI",
    "Dashboard": "Y",
    "UVI_Companion": "Y",
    "Episode_Used": "Y",
    "Description": "Need driver confirmation"
  }
]